AUTHORS.rst
CONTRIBUTING.rst
HISTORY.rst
LICENSE
MANIFEST.in
README.rst
setup.cfg
setup.py
django_meta_image_fixed.egg-info/PKG-INFO
django_meta_image_fixed.egg-info/SOURCES.txt
django_meta_image_fixed.egg-info/dependency_links.txt
django_meta_image_fixed.egg-info/requires.txt
django_meta_image_fixed.egg-info/top_level.txt
meta/__init__.py
meta/compat.py
meta/models.py
meta/settings.py
meta/views.py
meta/templates/meta.html
meta/templates/meta/meta.html
meta/templates/meta_mixin/meta.html
meta/templatetags/__init__.py
meta/templatetags/meta.py
meta/templatetags/meta_extra.py
meta_mixin/__init__.py